pytest_comfyui/__init__.py
pytest_comfyui-0.0.1.dist-info/METADATA
pytest_comfyui-0.0.1.dist-info/WHEEL
pytest_comfyui-0.0.1.dist-info/RECORD
