Metadata-Version: 2.4
Name: pytest-comfyui
Version: 0.0.1
Summary: Integration testing framework for ComfyUI nodes and workflows.
Project-URL: Homepage, https://github.com/yourusername/pytest-comfyui
Project-URL: Bug Tracker, https://github.com/yourusername/pytest-comfyui/issues
Author-email: Dwi Rizki Irawan <dwi.rizki.irawan@gmail.com>
Classifier: Framework :: Pytest
Classifier: License :: OSI Approved :: MIT License
Classifier: Operating System :: OS Independent
Classifier: Programming Language :: Python :: 3
Requires-Python: >=3.8
